{
  "scope": "wolfMQTT-master 301-336 partial+unsatisfied",
  "total_reviewed": 16,
  "status_summary": {
    "partialsatisfied": 12,
    "[non-English text removed]satisfied": 4
  },
  "risk_summary": {
    "low": 0,
    "medium": 0,
    "high": 16
  },
  "category_summary": {
    "Will Flag=0 [non-English text removed]": {
      "count": 4,
      "partial": 4,
      "unsatisfied": 0
    },
    "Will QoS validvaluevalidation[non-English text removed]": {
      "count": 3,
      "partial": 0,
      "unsatisfied": 3
    },
    "Will QoS/Retain [non-English text removed]": {
      "count": 5,
      "partial": 5,
      "unsatisfied": 0
    },
    "Will topic UTF-8 semanticvalidation[non-English text removed]": {
      "count": 3,
      "partial": 3,
      "unsatisfied": 0
    },
    "Will topic [non-English text removed]（U+0000）": {
      "count": 1,
      "partial": 0,
      "unsatisfied": 1
    }
  },
  "results": [
    {
      "id": 305,
      "status": "partialsatisfied",
      "category": "Will Flag=0 [non-English text removed]",
      "risk_level": "high",
      "reason": "may[non-English text removed]。",
      "variable_name": "Will Message",
      "change_action": "must be absent",
      "change_condition": "If the Will Flag is set to 0",
      "source_index": 304,
      "source_chunk_id": "chunk_0006",
      "original_comment": "Will Flag=0 [non-English text removed]validation。",
      "evidence_in_wolfmqtt": [
        "wolfMQTT-master/src/mqtt_packet.c:1048",
        "wolfMQTT-master/src/mqtt_packet.c:1118",
        "wolfMQTT-master/src/mqtt_packet.c:1145"
      ]
    },
    {
      "id": 306,
      "status": "partialsatisfied",
      "category": "Will Flag=0 [non-English text removed]",
      "risk_level": "high",
      "reason": "protocol[non-English text removed]。",
      "variable_name": "Will Message",
      "change_action": "must be absent",
      "change_condition": "If the Will Flag is set to 0",
      "source_index": 305,
      "source_chunk_id": "chunk_0018",
      "original_comment": "same as ID305：missing[non-English text removed]explicitrejection。",
      "evidence_in_wolfmqtt": [
        "wolfMQTT-master/src/mqtt_packet.c:1048",
        "wolfMQTT-master/src/mqtt_packet.c:1142",
        "wolfMQTT-master/src/mqtt_packet.c:1145"
      ]
    },
    {
      "id": 315,
      "status": "partialsatisfied",
      "category": "Will QoS/Retain [non-English text removed]",
      "risk_level": "high",
      "reason": "[non-English text removed]。",
      "variable_name": "Will QoS",
      "change_action": "set to constant",
      "change_condition": "If the Will Flag is set to 0",
      "source_index": 314,
      "source_chunk_id": "chunk_0006",
      "original_comment": "encoding side[non-English text removed]validation Will Flag=0 [non-English text removed] 0。",
      "evidence_in_wolfmqtt": [
        "wolfMQTT-master/src/mqtt_packet.c:872",
        "wolfMQTT-master/src/mqtt_packet.c:875",
        "wolfMQTT-master/src/mqtt_packet.c:1053"
      ]
    },
    {
      "id": 316,
      "status": "partialsatisfied",
      "category": "Will QoS/Retain [non-English text removed]",
      "risk_level": "high",
      "reason": "flag bits[non-English text removed]。",
      "variable_name": "Will QoS",
      "change_action": "must equal",
      "change_condition": "If the Will Flag is set to 0",
      "source_index": 315,
      "source_chunk_id": "chunk_0018",
      "original_comment": "same as ID315：missing[non-English text removed]protocolrejection。",
      "evidence_in_wolfmqtt": [
        "wolfMQTT-master/src/mqtt_packet.c:1000",
        "wolfMQTT-master/src/mqtt_packet.c:1053",
        "wolfMQTT-master/src/mqtt_packet.c:1145"
      ]
    },
    {
      "id": 317,
      "status": "partialsatisfied",
      "category": "Will QoS/Retain [non-English text removed]",
      "risk_level": "high",
      "reason": "protocol[non-English text removed]。",
      "variable_name": "Will QoS",
      "change_action": "set to constant",
      "change_condition": "If the Will Flag is set to 0",
      "source_index": 316,
      "source_chunk_id": "chunk_0018",
      "original_comment": "same as ID315/316：[non-English text removed]mandatoryvalidation。",
      "evidence_in_wolfmqtt": [
        "wolfMQTT-master/src/mqtt_packet.c:1001",
        "wolfMQTT-master/src/mqtt_packet.c:1054",
        "wolfMQTT-master/src/mqtt_packet.c:1142"
      ]
    },
    {
      "id": 318,
      "status": "[non-English text removed]satisfied",
      "category": "Will QoS validvaluevalidation[non-English text removed]",
      "risk_level": "high",
      "reason": "Will QoS reserved valuemay[non-English text removed]processingpath。",
      "variable_name": "Will QoS",
      "change_action": "validated range check",
      "change_condition": "If the Will Flag is set to 1",
      "source_index": 317,
      "source_chunk_id": "chunk_0006",
      "original_comment": "not found[non-English text removed] Will QoS=3（reserved value）[non-English text removed]。",
      "evidence_in_wolfmqtt": [
        "wolfMQTT-master/src/mqtt_packet.c:1053",
        "wolfMQTT-master/src/mqtt_packet.c:1054",
        "wolfMQTT-master/wolfmqtt/mqtt_packet.h:323"
      ]
    },
    {
      "id": 319,
      "status": "[non-English text removed]satisfied",
      "category": "Will QoS validvaluevalidation[non-English text removed]",
      "risk_level": "high",
      "reason": "protocolreserved value[non-English text removed]。",
      "variable_name": "Will QoS",
      "change_action": "validated membership check",
      "change_condition": "If the Will Flag is set to 1",
      "source_index": 318,
      "source_chunk_id": "chunk_0018",
      "original_comment": "same as ID318：[non-English text removed] {0,1,2}。",
      "evidence_in_wolfmqtt": [
        "wolfMQTT-master/src/mqtt_packet.c:1054",
        "wolfMQTT-master/src/mqtt_broker.c:2833",
        "wolfMQTT-master/wolfmqtt/mqtt_packet.h:335"
      ]
    },
    {
      "id": 320,
      "status": "[non-English text removed]satisfied",
      "category": "Will QoS validvaluevalidation[non-English text removed]",
      "risk_level": "high",
      "reason": "may[non-English text removed]。",
      "variable_name": "Will QoS",
      "change_action": "must not equal",
      "change_condition": "If the Will Flag is set to 1",
      "source_index": 319,
      "source_chunk_id": "chunk_0018",
      "original_comment": "same as ID318/319：Will QoS=3 [non-English text removed]error。",
      "evidence_in_wolfmqtt": [
        "wolfMQTT-master/src/mqtt_packet.c:1054",
        "wolfMQTT-master/src/mqtt_broker.c:2833",
        "wolfMQTT-master/src/mqtt_packet.c:1145"
      ]
    },
    {
      "id": 322,
      "status": "partialsatisfied",
      "category": "Will QoS/Retain [non-English text removed]",
      "risk_level": "high",
      "reason": "[non-English text removed]。",
      "variable_name": "Will Retain",
      "change_action": "set to constant",
      "change_condition": "If the Will Flag is set to 0",
      "source_index": 321,
      "source_chunk_id": "chunk_0006",
      "original_comment": "encoding side[non-English text removed]。",
      "evidence_in_wolfmqtt": [
        "wolfMQTT-master/src/mqtt_packet.c:872",
        "wolfMQTT-master/src/mqtt_packet.c:879",
        "wolfMQTT-master/src/mqtt_packet.c:1056"
      ]
    },
    {
      "id": 323,
      "status": "partialsatisfied",
      "category": "Will QoS/Retain [non-English text removed]",
      "risk_level": "high",
      "reason": "protocol[non-English text removed]。",
      "variable_name": "Will Retain",
      "change_action": "must equal",
      "change_condition": "If the Will Flag is set to 0",
      "source_index": 322,
      "source_chunk_id": "chunk_0018",
      "original_comment": "same as ID322：Will Flag=0 [non-English text removed]。",
      "evidence_in_wolfmqtt": [
        "wolfMQTT-master/src/mqtt_packet.c:1000",
        "wolfMQTT-master/src/mqtt_packet.c:1056",
        "wolfMQTT-master/src/mqtt_packet.c:1145"
      ]
    },
    {
      "id": 327,
      "status": "partialsatisfied",
      "category": "Will Flag=0 [non-English text removed]",
      "risk_level": "high",
      "reason": "[non-English text removed]。",
      "variable_name": "Will topic",
      "change_action": "must be absent",
      "change_condition": "If the Will Flag is set to 0",
      "source_index": 326,
      "source_chunk_id": "chunk_0006",
      "original_comment": "Will Flag=0 [non-English text removed] Will topic payload。",
      "evidence_in_wolfmqtt": [
        "wolfMQTT-master/src/mqtt_packet.c:1048",
        "wolfMQTT-master/src/mqtt_packet.c:1087",
        "wolfMQTT-master/src/mqtt_packet.c:1145"
      ]
    },
    {
      "id": 328,
      "status": "partialsatisfied",
      "category": "Will Flag=0 [non-English text removed]",
      "risk_level": "high",
      "reason": "[non-English text removed]。",
      "variable_name": "Will topic",
      "change_action": "must be absent",
      "change_condition": "If the Will Flag is set to 0",
      "source_index": 327,
      "source_chunk_id": "chunk_0018",
      "original_comment": "same as ID327：[non-English text removed]。",
      "evidence_in_wolfmqtt": [
        "wolfMQTT-master/src/mqtt_packet.c:1000",
        "wolfMQTT-master/src/mqtt_packet.c:1048",
        "wolfMQTT-master/src/mqtt_packet.c:1142"
      ]
    },
    {
      "id": 330,
      "status": "partialsatisfied",
      "category": "Will topic UTF-8 semanticvalidation[non-English text removed]",
      "risk_level": "high",
      "reason": "[non-English text removed] malformed UTF-8 Will topic。",
      "variable_name": "Will topic",
      "change_action": "must be valid UTF-8; invalid if value check fails",
      "change_condition": "The character data in a UTF-8 encoded string is carried in a Control Packet.",
      "source_index": 329,
      "source_chunk_id": "chunk_0017",
      "original_comment": "Will topic [non-English text removed]validation。",
      "evidence_in_wolfmqtt": [
        "wolfMQTT-master/src/mqtt_packet.c:1087",
        "wolfMQTT-master/src/mqtt_packet.c:338",
        "wolfMQTT-master/src/mqtt_packet.c:346"
      ]
    },
    {
      "id": 333,
      "status": "partialsatisfied",
      "category": "Will topic UTF-8 semanticvalidation[non-English text removed]",
      "risk_level": "high",
      "reason": "[non-English text removed]validation。",
      "variable_name": "Will topic",
      "change_action": "must satisfy validity check",
      "change_condition": "Will Topic field validation",
      "source_index": 332,
      "source_chunk_id": "chunk_0018",
      "original_comment": "Will topic [non-English text removed]。",
      "evidence_in_wolfmqtt": [
        "wolfMQTT-master/src/mqtt_packet.c:1087",
        "wolfMQTT-master/src/mqtt_packet.c:338",
        "wolfMQTT-master/src/mqtt_packet.c:366"
      ]
    },
    {
      "id": 334,
      "status": "partialsatisfied",
      "category": "Will topic UTF-8 semanticvalidation[non-English text removed]",
      "risk_level": "high",
      "reason": "[non-English text removed]。",
      "variable_name": "Will topic",
      "change_action": "must be valid UTF-8; invalid if value check fails",
      "change_condition": "Will topic contains UTF-8 character data",
      "source_index": 333,
      "source_chunk_id": "chunk_0004",
      "original_comment": "same as ID330/333：Will topic [non-English text removed]semanticvalidation。",
      "evidence_in_wolfmqtt": [
        "wolfMQTT-master/src/mqtt_packet.c:1087",
        "wolfMQTT-master/src/mqtt_packet.c:338",
        "wolfMQTT-master/src/mqtt_packet.c:346"
      ]
    },
    {
      "id": 335,
      "status": "[non-English text removed]satisfied",
      "category": "Will topic [non-English text removed]（U+0000）",
      "risk_level": "high",
      "reason": "NUL [non-English text removed]。",
      "variable_name": "Will topic",
      "change_action": "must not equal or include U+0000; invalid if value check fails",
      "change_condition": "Will topic contains encoding of null character U+0000",
      "source_index": 334,
      "source_chunk_id": "chunk_0004",
      "original_comment": "not found[non-English text removed] Will topic medium U+0000 [non-English text removed]explicitrejection。",
      "evidence_in_wolfmqtt": [
        "wolfMQTT-master/src/mqtt_packet.c:1087",
        "wolfMQTT-master/src/mqtt_packet.c:338",
        "wolfMQTT-master/src/mqtt_broker.c:2803"
      ]
    }
  ]
}